mykrok/__init__.py
mykrok/__main__.py
mykrok/_version.py
mykrok/cli.py
mykrok/config.py
mykrok/assets/mykrok-icon.png
mykrok/assets/mykrok-icon.svg
mykrok/assets/hyparquet/VERSION
mykrok/assets/hyparquet/assemble.js
mykrok/assets/hyparquet/column.js
mykrok/assets/hyparquet/constants.js
mykrok/assets/hyparquet/convert.js
mykrok/assets/hyparquet/datapage.js
mykrok/assets/hyparquet/delta.js
mykrok/assets/hyparquet/encoding.js
mykrok/assets/hyparquet/filter.js
mykrok/assets/hyparquet/geoparquet.js
mykrok/assets/hyparquet/index.js
mykrok/assets/hyparquet/indexes.js
mykrok/assets/hyparquet/metadata.js
mykrok/assets/hyparquet/plain.js
mykrok/assets/hyparquet/plan.js
mykrok/assets/hyparquet/query.js
mykrok/assets/hyparquet/read.js
mykrok/assets/hyparquet/rowgroup.js
mykrok/assets/hyparquet/schema.js
mykrok/assets/hyparquet/snappy.js
mykrok/assets/hyparquet/thrift.js
mykrok/assets/hyparquet/utils.js
mykrok/assets/hyparquet/wkb.js
mykrok/assets/leaflet/VERSION
mykrok/assets/leaflet/leaflet-src.js.map
mykrok/assets/leaflet/leaflet.css
mykrok/assets/leaflet/leaflet.js
mykrok/assets/leaflet/images/layers-2x.png
mykrok/assets/leaflet/images/layers.png
mykrok/assets/leaflet/images/marker-icon-2x.png
mykrok/assets/leaflet/images/marker-icon.png
mykrok/assets/leaflet/images/marker-shadow.png
mykrok/assets/map-browser/date-utils.js
mykrok/assets/map-browser/map-browser.js
mykrok/assets/map-browser/photo-viewer-utils.js
mykrok/assets/map-browser/tsv-utils.js
mykrok/lib/__init__.py
mykrok/lib/gpx.py
mykrok/lib/logging.py
mykrok/lib/parquet.py
mykrok/lib/paths.py
mykrok/models/__init__.py
mykrok/models/activity.py
mykrok/models/athlete.py
mykrok/models/state.py
mykrok/models/tracking.py
mykrok/services/__init__.py
mykrok/services/backup.py
mykrok/services/datalad.py
mykrok/services/fittrackee.py
mykrok/services/gh_pages.py
mykrok/services/migrate.py
mykrok/services/rate_limiter.py
mykrok/services/strava.py
mykrok/services/timezone.py
mykrok/views/__init__.py
mykrok/views/map.py
mykrok-1.4.1.dist-info/METADATA
mykrok-1.4.1.dist-info/WHEEL
mykrok-1.4.1.dist-info/entry_points.txt
mykrok-1.4.1.dist-info/RECORD
