Metadata-Version: 2.4
Name: mykrok
Version: 1.4.1
Summary: CLI tool to backup fitness activities with incremental sync, map visualization, and export (Strava supported)
Project-URL: Homepage, https://github.com/mykrok/mykrok
Project-URL: Documentation, https://mykrok.github.io/mykrok/
Project-URL: Repository, https://github.com/mykrok/mykrok
Project-URL: Issues, https://github.com/mykrok/mykrok/issues
Author: MyKrok contributors
License-Expression: Apache-2.0
Keywords: backup,fitness,fittrackee,gpx,mykrok,strava
Classifier: Development Status :: 3 - Alpha
Classifier: Environment :: Console
Classifier: Intended Audience :: End Users/Desktop
Classifier: License :: OSI Approved :: Apache Software License
Classifier: Operating System :: OS Independent
Classifier: Programming Language :: Python :: 3
Classifier: Programming Language :: Python :: 3.10
Classifier: Programming Language :: Python :: 3.11
Classifier: Programming Language :: Python :: 3.12
Classifier: Programming Language :: Python :: 3.13
Classifier: Topic :: Internet :: WWW/HTTP
Classifier: Topic :: System :: Archiving :: Backup
Requires-Python: >=3.10
Requires-Dist: click>=8.0
Requires-Dist: datalad>=1.0
Requires-Dist: duckdb>=0.9
Requires-Dist: pyarrow>=14.0
Requires-Dist: requests>=2.28
Requires-Dist: stravalib>=2.0
Requires-Dist: tomli>=2.0; python_version < '3.11'
Requires-Dist: tomlkit>=0.12
Provides-Extra: ci
Requires-Dist: codespell>=2.2; extra == 'ci'
Requires-Dist: mypy>=1.0; extra == 'ci'
Requires-Dist: pre-commit>=3.0; extra == 'ci'
Requires-Dist: pytest-cov>=4.0; extra == 'ci'
Requires-Dist: pytest-docker>=2.0; extra == 'ci'
Requires-Dist: pytest-timeout>=2.0; extra == 'ci'
Requires-Dist: pytest>=7.0; extra == 'ci'
Requires-Dist: responses>=0.23; extra == 'ci'
Requires-Dist: ruff>=0.1.0; extra == 'ci'
Requires-Dist: tox-gh-actions>=3.0; extra == 'ci'
Requires-Dist: tox-uv>=1.0; extra == 'ci'
Requires-Dist: tox>=4.0; extra == 'ci'
Requires-Dist: types-requests; extra == 'ci'
Provides-Extra: devel
Requires-Dist: codespell>=2.2; extra == 'devel'
Requires-Dist: mypy>=1.0; extra == 'devel'
Requires-Dist: pre-commit>=3.0; extra == 'devel'
Requires-Dist: pytest-cov>=4.0; extra == 'devel'
Requires-Dist: pytest-docker>=2.0; extra == 'devel'
Requires-Dist: pytest-timeout>=2.0; extra == 'devel'
Requires-Dist: pytest>=7.0; extra == 'devel'
Requires-Dist: responses>=0.23; extra == 'devel'
Requires-Dist: ruff>=0.1.0; extra == 'devel'
Requires-Dist: tox-uv>=1.0; extra == 'devel'
Requires-Dist: tox>=4.0; extra == 'devel'
Requires-Dist: types-requests; extra == 'devel'
Provides-Extra: docs
Requires-Dist: mkdocs-material>=9.5; extra == 'docs'
Requires-Dist: mkdocs>=1.5; extra == 'docs'
Requires-Dist: mkdocstrings[python]>=0.24; extra == 'docs'
Provides-Extra: e2e
Requires-Dist: pytest-cov>=4.0; extra == 'e2e'
Requires-Dist: pytest-docker>=2.0; extra == 'e2e'
Requires-Dist: pytest-playwright>=0.4.0; extra == 'e2e'
Requires-Dist: pytest-timeout>=2.0; extra == 'e2e'
Requires-Dist: pytest>=7.0; extra == 'e2e'
Requires-Dist: responses>=0.23; extra == 'e2e'
Provides-Extra: full
Requires-Dist: timezonefinder>=6.0; extra == 'full'
Provides-Extra: test
Requires-Dist: pytest-cov>=4.0; extra == 'test'
Requires-Dist: pytest-docker>=2.0; extra == 'test'
Requires-Dist: pytest-timeout>=2.0; extra == 'test'
Requires-Dist: pytest>=7.0; extra == 'test'
Requires-Dist: responses>=0.23; extra == 'test'
Provides-Extra: timezone
Requires-Dist: timezonefinder>=6.0; extra == 'timezone'
